{"Id":105,"SetName":"国际医学园区卷内目录","ExcelType":1,"ExcelTemplateFile":"OutputExcelTemplateFile/105/卷内.xls","ToExcelSet":"{  \"excelSet\": {    \"totalRow\": 360,    \"pageRow\": 18,    \"topRow\": 3  },  \"colRef\": [    {      \"field\": \"文件序号\",      \"excel\": \"A3\"    },    {      \"field\": \"文件编号\",      \"excel\": \"B3\"    },    {      \"field\": \"责任者\",      \"excel\": \"C3\"    },    {      \"field\": \"题名\",      \"excel\": \"D3\"    },    {      \"field\": \"文件日期\",      \"excel\": \"E3\"    },    {      \"field\": \"文件页数\",      \"excel\": \"F3\"    },    {      \"field\": \"备注\",      \"excel\": \"G3\"    },    {      \"field\": \"案卷顺序号\",      \"excel\": \"C2\"    }  ]}"}